preprocess_cancellation.py
preprocess_cancellation-0.1.5.post1.dist-info/entry_points.txt
preprocess_cancellation-0.1.5.post1.dist-info/WHEEL
preprocess_cancellation-0.1.5.post1.dist-info/METADATA
preprocess_cancellation-0.1.5.post1.dist-info/RECORD
